{
  "type": "Feature",
  "stac_version": "1.0.0",
  "id": "Sentinel-1_VV_ja_VH_osakuvat_2021-06-14_050308",
  "properties": {
    "datetime": null,
    "start_datetime": "2021-06-14T05:03:08Z",
    "end_datetime": "2021-06-14T05:04:27Z",
    "orbit": "DESCENDING"
  },
  "geometry": {
    "type": "Polygon",
    "coordinates": [
      [
        [
          19.33587,
          66.722017
        ],
        [
          28.5364,
          66.900835
        ],
        [
          28.961799,
          72.108628
        ],
        [
          17.248795,
          71.873197
        ],
        [
          19.33587,
          66.722017
        ]
      ]
    ]
  },
  "links": [
    {
      "rel": "root",
      "href": "../../catalog.json",
      "type": "application/json"
    },
    {
      "rel": "collection",
      "href": "../collection.json",
      "type": "application/json",
      "title": "Sentinel-1 backscatter tiles: VV and VH polarisation (FMI Tuulihaukka)"
    },
    {
      "rel": "parent",
      "href": "../collection.json",
      "type": "application/json",
      "title": "Sentinel-1 backscatter tiles: VV and VH polarisation (FMI Tuulihaukka)"
    }
  ],
  "assets": {
    "vv": {
      "href": "https://pta.data.lit.fmi.fi/sen1/s1_grd_vv_prep/S1_processed_20210614_050308_050427_027348_034426_VV.tif",
      "type": "image/tiff; application=geotiff; profile=cloud-optimized",
      "title": "vv",
      "roles": [
        "data"
      ]
    },
    "vh": {
      "href": "https://pta.data.lit.fmi.fi/sen1/s1_grd_vh_prep/S1_processed_20210614_050308_050427_027348_034426_VH.tif",
      "type": "image/tiff; application=geotiff; profile=cloud-optimized",
      "title": "vh",
      "roles": [
        "data"
      ]
    },
    "metadata": {
      "href": "https://pta.data.lit.fmi.fi/sen1/s1_grd_meta_prep/S1_processed_20210614_050308_050427_027348_034426.dim",
      "title": "metadata",
      "roles": [
        "metadata"
      ]
    }
  },
  "bbox": [
    17.2487948427255,
    66.7220172893661,
    28.9617990517079,
    72.1086284884371
  ],
  "stac_extensions": [],
  "collection": "sentinel_1_tiles_at_fmi",
  "gsd": 10.0,
  "proj:epsg": 3067,
  "proj:transform": [
    10.0,
    0.0,
    162707.95146708866,
    0.0,
    -10.0,
    8002145.062536304,
    0.0,
    0.0,
    1.0
  ]
}