{
  "type": "Feature",
  "stac_version": "1.0.0",
  "id": "Sentinel-1_VV_ja_VH_osakuvat_2020-03-22_152550",
  "properties": {
    "datetime": null,
    "start_datetime": "2020-03-22T15:25:50Z",
    "end_datetime": "2020-03-22T15:26:15Z",
    "orbit": "ASCENDING"
  },
  "geometry": {
    "type": "Polygon",
    "coordinates": [
      [
        [
          27.559637,
          66.197468
        ],
        [
          33.708087,
          66.052651
        ],
        [
          34.299216,
          68.089963
        ],
        [
          27.609465,
          68.249922
        ],
        [
          27.559637,
          66.197468
        ]
      ]
    ]
  },
  "links": [
    {
      "rel": "root",
      "href": "../../catalog.json",
      "type": "application/json"
    },
    {
      "rel": "collection",
      "href": "../collection.json",
      "type": "application/json",
      "title": "Sentinel-1 backscatter tiles: VV and VH polarisation (FMI Tuulihaukka)"
    },
    {
      "rel": "parent",
      "href": "../collection.json",
      "type": "application/json",
      "title": "Sentinel-1 backscatter tiles: VV and VH polarisation (FMI Tuulihaukka)"
    }
  ],
  "assets": {
    "vv": {
      "href": "https://pta.data.lit.fmi.fi/sen1/s1_grd_vv_prep/S1_processed_20200322_152550_152615_031790_03AAD9_VV.tif",
      "type": "image/tiff; application=geotiff; profile=cloud-optimized",
      "title": "vv",
      "roles": [
        "data"
      ]
    },
    "vh": {
      "href": "https://pta.data.lit.fmi.fi/sen1/s1_grd_vh_prep/S1_processed_20200322_152550_152615_031790_03AAD9_VH.tif",
      "type": "image/tiff; application=geotiff; profile=cloud-optimized",
      "title": "vh",
      "roles": [
        "data"
      ]
    },
    "metadata": {
      "href": "https://pta.data.lit.fmi.fi/sen1/s1_grd_meta_prep/S1_processed_20200322_152550_152615_031790_03AAD9.dim",
      "title": "metadata",
      "roles": [
        "metadata"
      ]
    }
  },
  "bbox": [
    27.5596365310988,
    66.0526507989971,
    34.2992161114244,
    68.2499219578734
  ],
  "stac_extensions": [],
  "collection": "sentinel_1_tiles_at_fmi",
  "gsd": 20.0,
  "proj:epsg": 3067,
  "proj:transform": [
    20.0,
    0.0,
    525203.1586414345,
    0.0,
    -20.0,
    7570853.299960064,
    0.0,
    0.0,
    1.0
  ]
}