{
  "type": "Feature",
  "stac_version": "1.0.0",
  "id": "Sentinel-1_VV_ja_VH_osakuvat_2018-10-08_154900",
  "properties": {
    "datetime": null,
    "start_datetime": "2018-10-08T15:49:00Z",
    "end_datetime": "2018-10-08T15:49:25Z",
    "orbit": "ASCENDING"
  },
  "geometry": {
    "type": "Polygon",
    "coordinates": [
      [
        [
          23.141543,
          63.416899
        ],
        [
          28.66374,
          63.459296
        ],
        [
          28.786175,
          65.406559
        ],
        [
          22.858375,
          65.360316
        ],
        [
          23.141543,
          63.416899
        ]
      ]
    ]
  },
  "links": [
    {
      "rel": "license",
      "href": "https://sentinels.copernicus.eu/documents/247904/690755/Sentinel_Data_Legal_Notice",
      "title": "License"
    },
    {
      "rel": "root",
      "href": "../../catalog.json",
      "type": "application/json"
    },
    {
      "rel": "collection",
      "href": "../collection.json",
      "type": "application/json",
      "title": "Sentinel-1 backscatter tiles: VV and VH polarisation."
    },
    {
      "rel": "parent",
      "href": "../collection.json",
      "type": "application/json",
      "title": "Sentinel-1 backscatter tiles: VV and VH polarisation."
    }
  ],
  "assets": {
    "vv": {
      "href": "https://pta.data.lit.fmi.fi/sen1/s1_grd_vv_prep/S1_processed_20181008_154900_154925_013063_018225_VV.tif",
      "type": "image/tiff; application=geotiff; profile=cloud-optimized",
      "title": "vv",
      "roles": [
        "data"
      ]
    },
    "vh": {
      "href": "https://pta.data.lit.fmi.fi/sen1/s1_grd_vh_prep/S1_processed_20181008_154900_154925_013063_018225_VH.tif",
      "type": "image/tiff; application=geotiff; profile=cloud-optimized",
      "title": "vh",
      "roles": [
        "data"
      ]
    },
    "metadata": {
      "href": "https://pta.data.lit.fmi.fi/sen1/s1_grd_meta_prep/S1_processed_20181008_154900_154925_013063_018225.dim",
      "title": "metadata",
      "roles": [
        "metadata"
      ]
    }
  },
  "bbox": [
    22.8583747594492,
    63.4168989387857,
    28.7861749933629,
    65.4065593363805
  ],
  "stac_extensions": [],
  "collection": "sentinel_1_tiles_at_fmi",
  "gsd": 20.0,
  "proj:epsg": "EPSG:3067",
  "proj:transform": [
    20.0,
    0.0,
    307438.9394381209,
    0.0,
    -20.0,
    7254941.696921111,
    0.0,
    0.0,
    1.0
  ]
}