{
  "type": "Feature",
  "stac_version": "1.0.0",
  "id": "Sentinel-1_VV_ja_VH_osakuvat_2019-11-02_154950",
  "properties": {
    "datetime": null,
    "start_datetime": "2019-11-02T15:49:50Z",
    "end_datetime": "2019-11-02T15:50:15Z",
    "orbit": "ASCENDING"
  },
  "geometry": {
    "type": "Polygon",
    "coordinates": [
      [
        [
          23.130821,
          63.506547
        ],
        [
          28.612433,
          63.54972
        ],
        [
          28.731297,
          65.492528
        ],
        [
          22.846394,
          65.445438
        ],
        [
          23.130821,
          63.506547
        ]
      ]
    ]
  },
  "links": [
    {
      "rel": "license",
      "href": "https://sentinels.copernicus.eu/documents/247904/690755/Sentinel_Data_Legal_Notice",
      "title": "License"
    },
    {
      "rel": "root",
      "href": "../../catalog.json",
      "type": "application/json"
    },
    {
      "rel": "collection",
      "href": "../collection.json",
      "type": "application/json",
      "title": "Sentinel-1 backscatter tiles: VV and VH polarisation."
    },
    {
      "rel": "parent",
      "href": "../collection.json",
      "type": "application/json",
      "title": "Sentinel-1 backscatter tiles: VV and VH polarisation."
    }
  ],
  "assets": {
    "vv": {
      "href": "https://pta.data.lit.fmi.fi/sen1/s1_grd_vv_prep/S1_processed_20191102_154950_155015_029734_03636A_VV.tif",
      "type": "image/tiff; application=geotiff; profile=cloud-optimized",
      "title": "vv",
      "roles": [
        "data"
      ]
    },
    "vh": {
      "href": "https://pta.data.lit.fmi.fi/sen1/s1_grd_vh_prep/S1_processed_20191102_154950_155015_029734_03636A_VH.tif",
      "type": "image/tiff; application=geotiff; profile=cloud-optimized",
      "title": "vh",
      "roles": [
        "data"
      ]
    },
    "metadata": {
      "href": "https://pta.data.lit.fmi.fi/sen1/s1_grd_meta_prep/S1_processed_20191102_154950_155015_029734_03636A.dim",
      "title": "metadata",
      "roles": [
        "metadata"
      ]
    }
  },
  "bbox": [
    22.8463936823387,
    63.5065473748595,
    28.7312970371255,
    65.4925279588569
  ],
  "stac_extensions": [],
  "collection": "sentinel_1_tiles_at_fmi",
  "gsd": 20.0,
  "proj:epsg": "EPSG:3067",
  "proj:transform": [
    20.0,
    0.0,
    307507.90789820254,
    0.0,
    -20.0,
    7264449.312142762,
    0.0,
    0.0,
    1.0
  ]
}