{
  "type": "Feature",
  "stac_version": "1.0.0",
  "id": "Sentinel-1_VV_ja_VH_osakuvat_2016-12-25_170848",
  "properties": {
    "datetime": null,
    "start_datetime": "2016-12-25T17:08:48Z",
    "end_datetime": "2016-12-25T17:09:13Z",
    "orbit": "ASCENDING"
  },
  "geometry": {
    "type": "Polygon",
    "coordinates": [
      [
        [
          7.470224,
          52.332314
        ],
        [
          11.932025,
          53.004444
        ],
        [
          11.024267,
          55.367921
        ],
        [
          6.334117,
          54.636163
        ],
        [
          7.470224,
          52.332314
        ]
      ]
    ]
  },
  "links": [
    {
      "rel": "root",
      "href": "../../catalog.json",
      "type": "application/json"
    },
    {
      "rel": "collection",
      "href": "../collection.json",
      "type": "application/json",
      "title": "Sentinel-1 backscatter tiles: VV and VH polarisation."
    },
    {
      "rel": "parent",
      "href": "../collection.json",
      "type": "application/json",
      "title": "Sentinel-1 backscatter tiles: VV and VH polarisation."
    }
  ],
  "assets": {
    "vv": {
      "href": "https://pta.data.lit.fmi.fi/sen1/s1_grd_vv_prep/S1_processed_20161225_170848_170913_014539_0179C8_VV.tif",
      "type": "image/tiff; application=geotiff; profile=cloud-optimized",
      "title": "vv",
      "roles": [
        "data"
      ]
    },
    "vh": {
      "href": "https://pta.data.lit.fmi.fi/sen1/s1_grd_vh_prep/S1_processed_20161225_170848_170913_014539_0179C8_VH.tif",
      "type": "image/tiff; application=geotiff; profile=cloud-optimized",
      "title": "vh",
      "roles": [
        "data"
      ]
    },
    "metadata": {
      "href": "https://pta.data.lit.fmi.fi/sen1/s1_grd_meta_prep/S1_processed_20161225_170848_170913_014539_0179C8.dim",
      "title": "metadata",
      "roles": [
        "metadata"
      ]
    }
  },
  "bbox": [
    6.33411704487071,
    52.3323144101221,
    11.9320253681823,
    55.3679213964683
  ],
  "stac_extensions": [],
  "collection": "sentinel_1_tiles_at_fmi",
  "gsd": 20.0,
  "proj:epsg": "EPSG:3067",
  "proj:transform": [
    20.0,
    0.0,
    -823802.9385583773,
    0.0,
    -20.0,
    6252588.230456155,
    0.0,
    0.0,
    1.0
  ]
}