{
  "type": "Feature",
  "stac_version": "1.0.0",
  "id": "Sentinel-1_VV_ja_VH_osakuvat_2017-06-09_051935",
  "properties": {
    "datetime": null,
    "start_datetime": "2017-06-09T05:19:35Z",
    "end_datetime": "2017-06-09T05:20:08Z",
    "orbit": "DESCENDING"
  },
  "geometry": {
    "type": "Polygon",
    "coordinates": [
      [
        [
          16.67993,
          68.006644
        ],
        [
          22.214853,
          68.260735
        ],
        [
          21.724965,
          70.364033
        ],
        [
          15.644039,
          70.080545
        ],
        [
          16.67993,
          68.006644
        ]
      ]
    ]
  },
  "links": [
    {
      "rel": "license",
      "href": "https://sentinels.copernicus.eu/documents/247904/690755/Sentinel_Data_Legal_Notice",
      "title": "License"
    },
    {
      "rel": "root",
      "href": "../../catalog.json",
      "type": "application/json"
    },
    {
      "rel": "collection",
      "href": "../collection.json",
      "type": "application/json",
      "title": "Sentinel-1 backscatter tiles: VV and VH polarisation."
    },
    {
      "rel": "parent",
      "href": "../collection.json",
      "type": "application/json",
      "title": "Sentinel-1 backscatter tiles: VV and VH polarisation."
    }
  ],
  "assets": {
    "vv": {
      "href": "https://pta.data.lit.fmi.fi/sen1/s1_grd_vv_prep/S1_processed_20170609_051935_052008_005969_00A798_VV.tif",
      "type": "image/tiff; application=geotiff; profile=cloud-optimized",
      "title": "vv",
      "roles": [
        "data"
      ]
    },
    "vh": {
      "href": "https://pta.data.lit.fmi.fi/sen1/s1_grd_vh_prep/S1_processed_20170609_051935_052008_005969_00A798_VH.tif",
      "type": "image/tiff; application=geotiff; profile=cloud-optimized",
      "title": "vh",
      "roles": [
        "data"
      ]
    },
    "metadata": {
      "href": "https://pta.data.lit.fmi.fi/sen1/s1_grd_meta_prep/S1_processed_20170609_051935_052008_005969_00A798.dim",
      "title": "metadata",
      "roles": [
        "metadata"
      ]
    }
  },
  "bbox": [
    15.6440393999154,
    68.0066436327658,
    22.2148530610205,
    70.3640328119958
  ],
  "stac_extensions": [],
  "collection": "sentinel_1_tiles_at_fmi",
  "gsd": 80.0,
  "proj:epsg": "EPSG:3067",
  "proj:transform": [
    80.0,
    0.0,
    70377.91929335415,
    0.0,
    -80.0,
    7815045.566953223,
    0.0,
    0.0,
    1.0
  ]
}