{
  "type": "Feature",
  "stac_version": "1.0.0",
  "id": "Sentinel-1_VV_ja_VH_osakuvat_2017-05-20_044922",
  "properties": {
    "datetime": null,
    "start_datetime": "2017-05-20T04:49:22Z",
    "end_datetime": "2017-05-20T04:49:47Z",
    "orbit": "DESCENDING"
  },
  "geometry": {
    "type": "Polygon",
    "coordinates": [
      [
        [
          20.542904,
          58.850839
        ],
        [
          25.490153,
          59.003506
        ],
        [
          25.394178,
          61.042296
        ],
        [
          20.136047,
          60.876677
        ],
        [
          20.542904,
          58.850839
        ]
      ]
    ]
  },
  "links": [
    {
      "rel": "root",
      "href": "../../catalog.json",
      "type": "application/json"
    },
    {
      "rel": "collection",
      "href": "../collection.json",
      "type": "application/json",
      "title": "Sentinel-1 backscatter tiles: VV and VH polarisation (FMI Tuulituhohaukka)"
    },
    {
      "rel": "parent",
      "href": "../collection.json",
      "type": "application/json",
      "title": "Sentinel-1 backscatter tiles: VV and VH polarisation (FMI Tuulituhohaukka)"
    }
  ],
  "assets": {
    "vv": {
      "href": "https://pta.data.lit.fmi.fi/sen1/s1_grd_vv_prep/S1_processed_20170520_044922_044947_005677_009F1C_VV.tif",
      "type": "image/tiff; application=geotiff; profile=cloud-optimized",
      "title": "vv",
      "roles": [
        "data"
      ]
    },
    "vh": {
      "href": "https://pta.data.lit.fmi.fi/sen1/s1_grd_vh_prep/S1_processed_20170520_044922_044947_005677_009F1C_VH.tif",
      "type": "image/tiff; application=geotiff; profile=cloud-optimized",
      "title": "vh",
      "roles": [
        "data"
      ]
    },
    "metadata": {
      "href": "https://pta.data.lit.fmi.fi/sen1/s1_grd_meta_prep/S1_processed_20170520_044922_044947_005677_009F1C.dim",
      "title": "metadata",
      "roles": [
        "metadata"
      ]
    }
  },
  "bbox": [
    20.1360471340479,
    58.8508393248467,
    25.4901526898444,
    61.0422963867088
  ],
  "stac_extensions": [],
  "collection": "sentinel_1_tiles_at_fmi",
  "gsd": 20.0,
  "proj:epsg": 3067,
  "proj:transform": [
    20.0,
    0.0,
    127789.31373946148,
    0.0,
    -20.0,
    6768562.074021341,
    0.0,
    0.0,
    1.0
  ]
}