{
  "type": "Feature",
  "stac_version": "1.0.0",
  "id": "Sentinel-1_VV_ja_VH_osakuvat_2017-06-02_155714",
  "properties": {
    "datetime": null,
    "start_datetime": "2017-06-02T15:57:14Z",
    "end_datetime": "2017-06-02T15:57:46Z",
    "orbit": "ASCENDING"
  },
  "geometry": {
    "type": "Polygon",
    "coordinates": [
      [
        [
          22.441733,
          62.091844
        ],
        [
          26.487644,
          62.166017
        ],
        [
          26.452343,
          64.101688
        ],
        [
          22.12911,
          64.021076
        ],
        [
          22.441733,
          62.091844
        ]
      ]
    ]
  },
  "links": [
    {
      "rel": "root",
      "href": "../../catalog.json",
      "type": "application/json"
    },
    {
      "rel": "collection",
      "href": "../collection.json",
      "type": "application/json",
      "title": "Sentinel-1 backscatter tiles: VV and VH polarisation."
    },
    {
      "rel": "parent",
      "href": "../collection.json",
      "type": "application/json",
      "title": "Sentinel-1 backscatter tiles: VV and VH polarisation."
    }
  ],
  "assets": {
    "vv": {
      "href": "https://pta.data.lit.fmi.fi/sen1/s1_grd_vv_prep/S1_processed_20170602_155714_155746_016857_01C07D_VV.tif",
      "type": "image/tiff; application=geotiff; profile=cloud-optimized",
      "title": "vv",
      "roles": [
        "data"
      ]
    },
    "vh": {
      "href": "https://pta.data.lit.fmi.fi/sen1/s1_grd_vh_prep/S1_processed_20170602_155714_155746_016857_01C07D_VH.tif",
      "type": "image/tiff; application=geotiff; profile=cloud-optimized",
      "title": "vh",
      "roles": [
        "data"
      ]
    },
    "metadata": {
      "href": "https://pta.data.lit.fmi.fi/sen1/s1_grd_meta_prep/S1_processed_20170602_155714_155746_016857_01C07D.dim",
      "title": "metadata",
      "roles": [
        "metadata"
      ]
    }
  },
  "bbox": [
    22.1291102329138,
    62.0918440391845,
    26.4876441068842,
    64.1016884329504
  ],
  "stac_extensions": [],
  "collection": "sentinel_1_tiles_at_fmi",
  "gsd": 80.0,
  "proj:epsg": "EPSG:3067",
  "proj:transform": [
    80.0,
    0.0,
    262110.52836420102,
    0.0,
    -80.0,
    7108460.41007258,
    0.0,
    0.0,
    1.0
  ]
}