{
  "type": "Feature",
  "stac_version": "1.0.0",
  "id": "Sentinel-1_VV_ja_VH_osakuvat_2020-05-13_154028",
  "properties": {
    "datetime": null,
    "start_datetime": "2020-05-13T15:40:28Z",
    "end_datetime": "2020-05-13T15:40:53Z",
    "orbit": "ASCENDING"
  },
  "geometry": {
    "type": "Polygon",
    "coordinates": [
      [
        [
          25.984716,
          62.087598
        ],
        [
          31.200383,
          62.027441
        ],
        [
          31.489932,
          63.971634
        ],
        [
          25.914467,
          64.037046
        ],
        [
          25.984716,
          62.087598
        ]
      ]
    ]
  },
  "links": [
    {
      "rel": "root",
      "href": "../../catalog.json",
      "type": "application/json"
    },
    {
      "rel": "collection",
      "href": "../collection.json",
      "type": "application/json",
      "title": "Sentinel-1 backscatter tiles: VV and VH polarisation."
    },
    {
      "rel": "parent",
      "href": "../collection.json",
      "type": "application/json",
      "title": "Sentinel-1 backscatter tiles: VV and VH polarisation."
    }
  ],
  "assets": {
    "vv": {
      "href": "https://pta.data.lit.fmi.fi/sen1/s1_grd_vv_prep/S1_processed_20200513_154028_154053_021565_028F15_VV.tif",
      "type": "image/tiff; application=geotiff; profile=cloud-optimized",
      "title": "vv",
      "roles": [
        "data"
      ]
    },
    "vh": {
      "href": "https://pta.data.lit.fmi.fi/sen1/s1_grd_vh_prep/S1_processed_20200513_154028_154053_021565_028F15_VH.tif",
      "type": "image/tiff; application=geotiff; profile=cloud-optimized",
      "title": "vh",
      "roles": [
        "data"
      ]
    },
    "metadata": {
      "href": "https://pta.data.lit.fmi.fi/sen1/s1_grd_meta_prep/S1_processed_20200513_154028_154053_021565_028F15.dim",
      "title": "metadata",
      "roles": [
        "metadata"
      ]
    }
  },
  "bbox": [
    25.9144665484309,
    62.0274406498586,
    31.4899315471048,
    64.0370455364041
  ],
  "stac_extensions": [],
  "collection": "sentinel_1_tiles_at_fmi",
  "gsd": 19.999999999999996,
  "proj:epsg": "EPSG:3067",
  "proj:transform": [
    19.999999999999996,
    0.0,
    446976.4669284283,
    0.0,
    -19.999999999999996,
    7101593.880335623,
    0.0,
    0.0,
    1.0
  ]
}