{
  "type": "Feature",
  "stac_version": "1.0.0",
  "id": "Sentinel-1_VV_ja_VH_osakuvat_2017-06-03_052014",
  "properties": {
    "datetime": null,
    "start_datetime": "2017-06-03T05:20:14Z",
    "end_datetime": "2017-06-03T05:20:39Z",
    "orbit": "DESCENDING"
  },
  "geometry": {
    "type": "Polygon",
    "coordinates": [
      [
        [
          16.176744,
          68.449198
        ],
        [
          23.574031,
          68.763949
        ],
        [
          23.186716,
          71.007768
        ],
        [
          14.983632,
          70.653189
        ],
        [
          16.176744,
          68.449198
        ]
      ]
    ]
  },
  "links": [
    {
      "rel": "root",
      "href": "../../catalog.json",
      "type": "application/json"
    },
    {
      "rel": "collection",
      "href": "../collection.json",
      "type": "application/json",
      "title": "Sentinel-1 backscatter tiles: VV and VH polarisation (FMI Tuulituhohaukka)"
    },
    {
      "rel": "parent",
      "href": "../collection.json",
      "type": "application/json",
      "title": "Sentinel-1 backscatter tiles: VV and VH polarisation (FMI Tuulituhohaukka)"
    }
  ],
  "assets": {
    "vv": {
      "href": "https://pta.data.lit.fmi.fi/sen1/s1_grd_vv_prep/S1_processed_20170603_052014_052039_016865_01C0C1_VV.tif",
      "type": "image/tiff; application=geotiff; profile=cloud-optimized",
      "title": "vv",
      "roles": [
        "data"
      ]
    },
    "vh": {
      "href": "https://pta.data.lit.fmi.fi/sen1/s1_grd_vh_prep/S1_processed_20170603_052014_052039_016865_01C0C1_VH.tif",
      "type": "image/tiff; application=geotiff; profile=cloud-optimized",
      "title": "vh",
      "roles": [
        "data"
      ]
    },
    "metadata": {
      "href": "https://pta.data.lit.fmi.fi/sen1/s1_grd_meta_prep/S1_processed_20170603_052014_052039_016865_01C0C1.dim",
      "title": "metadata",
      "roles": [
        "metadata"
      ]
    }
  },
  "bbox": [
    14.9836323922875,
    68.4491976687161,
    23.5740311980871,
    71.0077684170219
  ],
  "stac_extensions": [],
  "collection": "sentinel_1_tiles_at_fmi",
  "gsd": 20.0,
  "proj:epsg": 3067,
  "proj:transform": [
    20.0,
    0.0,
    58253.79337126558,
    0.0,
    -20.0,
    7882620.799201748,
    0.0,
    0.0,
    1.0
  ]
}