{
  "type": "Feature",
  "stac_version": "1.0.0",
  "id": "Sentinel-1_VV_ja_VH_osakuvat_2020-07-27_151735",
  "properties": {
    "datetime": null,
    "start_datetime": "2020-07-27T15:17:35Z",
    "end_datetime": "2020-07-27T15:18:00Z",
    "orbit": "ASCENDING"
  },
  "geometry": {
    "type": "Polygon",
    "coordinates": [
      [
        [
          29.785631,
          65.711739
        ],
        [
          35.923838,
          65.474395
        ],
        [
          36.717906,
          67.577458
        ],
        [
          30.037671,
          67.840074
        ],
        [
          29.785631,
          65.711739
        ]
      ]
    ]
  },
  "links": [
    {
      "rel": "root",
      "href": "../../catalog.json",
      "type": "application/json"
    },
    {
      "rel": "collection",
      "href": "../collection.json",
      "type": "application/json",
      "title": "Sentinel-1 backscatter tiles: VV and VH polarisation (FMI Tuulihaukka)"
    },
    {
      "rel": "parent",
      "href": "../collection.json",
      "type": "application/json",
      "title": "Sentinel-1 backscatter tiles: VV and VH polarisation (FMI Tuulihaukka)"
    }
  ],
  "assets": {
    "vv": {
      "href": "https://pta.data.lit.fmi.fi/sen1/s1_grd_vv_prep/S1_processed_20200727_151735_151800_033642_03E626_VV.tif",
      "type": "image/tiff; application=geotiff; profile=cloud-optimized",
      "title": "vv",
      "roles": [
        "data"
      ]
    },
    "vh": {
      "href": "https://pta.data.lit.fmi.fi/sen1/s1_grd_vh_prep/S1_processed_20200727_151735_151800_033642_03E626_VH.tif",
      "type": "image/tiff; application=geotiff; profile=cloud-optimized",
      "title": "vh",
      "roles": [
        "data"
      ]
    },
    "metadata": {
      "href": "https://pta.data.lit.fmi.fi/sen1/s1_grd_meta_prep/S1_processed_20200727_151735_151800_033642_03E626.dim",
      "title": "metadata",
      "roles": [
        "metadata"
      ]
    }
  },
  "bbox": [
    29.7856312726267,
    65.4743947895923,
    36.7179061181066,
    67.8400741048527
  ],
  "stac_extensions": [],
  "collection": "sentinel_1_tiles_at_fmi",
  "gsd": 20.0,
  "proj:epsg": 3067,
  "proj:transform": [
    20.0,
    0.0,
    627822.3615531108,
    0.0,
    -20.0,
    7528173.220083093,
    0.0,
    0.0,
    1.0
  ]
}