{
  "type": "Feature",
  "stac_version": "1.0.0",
  "id": "Sentinel-1_VV_ja_VH_osakuvat_2016-12-16_155625",
  "properties": {
    "datetime": null,
    "start_datetime": "2016-12-16T15:56:25Z",
    "end_datetime": "2016-12-16T15:56:50Z",
    "orbit": "ASCENDING"
  },
  "geometry": {
    "type": "Polygon",
    "coordinates": [
      [
        [
          23.422832,
          58.855899
        ],
        [
          28.1387,
          58.900414
        ],
        [
          28.206446,
          60.825026
        ],
        [
          23.210551,
          60.776955
        ],
        [
          23.422832,
          58.855899
        ]
      ]
    ]
  },
  "links": [
    {
      "rel": "root",
      "href": "../../catalog.json",
      "type": "application/json"
    },
    {
      "rel": "collection",
      "href": "../collection.json",
      "type": "application/json",
      "title": "Sentinel-1 backscatter tiles: VV and VH polarisation (FMI Tuulihaukka)"
    },
    {
      "rel": "parent",
      "href": "../collection.json",
      "type": "application/json",
      "title": "Sentinel-1 backscatter tiles: VV and VH polarisation (FMI Tuulihaukka)"
    }
  ],
  "assets": {
    "vv": {
      "href": "https://pta.data.lit.fmi.fi/sen1/s1_grd_vv_prep/S1_processed_20161216_155625_155650_014407_0175AA_VV.tif",
      "type": "image/tiff; application=geotiff; profile=cloud-optimized",
      "title": "vv",
      "roles": [
        "data"
      ]
    },
    "vh": {
      "href": "https://pta.data.lit.fmi.fi/sen1/s1_grd_vh_prep/S1_processed_20161216_155625_155650_014407_0175AA_VH.tif",
      "type": "image/tiff; application=geotiff; profile=cloud-optimized",
      "title": "vh",
      "roles": [
        "data"
      ]
    },
    "metadata": {
      "href": "https://pta.data.lit.fmi.fi/sen1/s1_grd_meta_prep/S1_processed_20161216_155625_155650_014407_0175AA.dim",
      "title": "metadata",
      "roles": [
        "metadata"
      ]
    }
  },
  "bbox": [
    23.2105513110303,
    58.8558993994257,
    28.2064463391707,
    60.8250264788532
  ],
  "stac_extensions": [],
  "collection": "sentinel_1_tiles_at_fmi",
  "gsd": 19.999999999999996,
  "proj:epsg": 3067,
  "proj:transform": [
    19.999999999999996,
    0.0,
    293687.72985618585,
    0.0,
    -19.999999999999996,
    6743901.396367032,
    0.0,
    0.0,
    1.0
  ]
}