{
  "type": "Feature",
  "stac_version": "1.0.0",
  "id": "Sentinel-1_VV_ja_VH_osakuvat_2017-05-09_150919",
  "properties": {
    "datetime": null,
    "start_datetime": "2017-05-09T15:09:19Z",
    "end_datetime": "2017-05-09T15:09:44Z",
    "orbit": "ASCENDING"
  },
  "geometry": {
    "type": "Polygon",
    "coordinates": [
      [
        [
          28.965039,
          69.438687
        ],
        [
          36.203451,
          69.204364
        ],
        [
          37.220046,
          71.336107
        ],
        [
          29.186328,
          71.59986
        ],
        [
          28.965039,
          69.438687
        ]
      ]
    ]
  },
  "links": [
    {
      "rel": "root",
      "href": "../../catalog.json",
      "type": "application/json"
    },
    {
      "rel": "collection",
      "href": "../collection.json",
      "type": "application/json",
      "title": "Sentinel-1 backscatter tiles: VV and VH polarisation (FMI Tuulihaukka)"
    },
    {
      "rel": "parent",
      "href": "../collection.json",
      "type": "application/json",
      "title": "Sentinel-1 backscatter tiles: VV and VH polarisation (FMI Tuulihaukka)"
    }
  ],
  "assets": {
    "vv": {
      "href": "https://pta.data.lit.fmi.fi/sen1/s1_grd_vv_prep/S1_processed_20170509_150919_150944_005523_009AD2_VV.tif",
      "type": "image/tiff; application=geotiff; profile=cloud-optimized",
      "title": "vv",
      "roles": [
        "data"
      ]
    },
    "vh": {
      "href": "https://pta.data.lit.fmi.fi/sen1/s1_grd_vh_prep/S1_processed_20170509_150919_150944_005523_009AD2_VH.tif",
      "type": "image/tiff; application=geotiff; profile=cloud-optimized",
      "title": "vh",
      "roles": [
        "data"
      ]
    },
    "metadata": {
      "href": "https://pta.data.lit.fmi.fi/sen1/s1_grd_meta_prep/S1_processed_20170509_150919_150944_005523_009AD2.dim",
      "title": "metadata",
      "roles": [
        "metadata"
      ]
    }
  },
  "bbox": [
    28.965038674533,
    69.204364090074,
    37.2200463035661,
    71.5998598400974
  ],
  "stac_extensions": [],
  "collection": "sentinel_1_tiles_at_fmi",
  "gsd": 20.0,
  "proj:epsg": 3067,
  "proj:transform": [
    20.0,
    0.0,
    577010.3029324937,
    0.0,
    -20.0,
    7945695.54617388,
    0.0,
    0.0,
    1.0
  ]
}