{
  "type": "Feature",
  "stac_version": "1.0.0",
  "id": "Sentinel-1_VV_ja_VH_osakuvat_2020-09-06_161322",
  "properties": {
    "datetime": null,
    "start_datetime": "2020-09-06T16:13:22Z",
    "end_datetime": "2020-09-06T16:14:41Z",
    "orbit": "ASCENDING"
  },
  "geometry": {
    "type": "Polygon",
    "coordinates": [
      [
        [
          16.34643,
          64.511018
        ],
        [
          22.313922,
          64.82248
        ],
        [
          21.897491,
          66.998962
        ],
        [
          15.419566,
          66.654625
        ],
        [
          16.34643,
          64.511018
        ]
      ]
    ]
  },
  "links": [
    {
      "rel": "root",
      "href": "../../catalog.json",
      "type": "application/json"
    },
    {
      "rel": "collection",
      "href": "../collection.json",
      "type": "application/json",
      "title": "Sentinel-1 backscatter tiles: VV and VH polarisation."
    },
    {
      "rel": "parent",
      "href": "../collection.json",
      "type": "application/json",
      "title": "Sentinel-1 backscatter tiles: VV and VH polarisation."
    }
  ],
  "assets": {
    "vv": {
      "href": "https://pta.data.lit.fmi.fi/sen1/s1_grd_vv_prep/S1_processed_20200906_161322_161441_023257_02C2A3_VV.tif",
      "type": "image/tiff; application=geotiff; profile=cloud-optimized",
      "title": "vv",
      "roles": [
        "data"
      ]
    },
    "vh": {
      "href": "https://pta.data.lit.fmi.fi/sen1/s1_grd_vh_prep/S1_processed_20200906_161322_161441_023257_02C2A3_VH.tif",
      "type": "image/tiff; application=geotiff; profile=cloud-optimized",
      "title": "vh",
      "roles": [
        "data"
      ]
    },
    "metadata": {
      "href": "https://pta.data.lit.fmi.fi/sen1/s1_grd_meta_prep/S1_processed_20200906_161322_161441_023257_02C2A3.dim",
      "title": "metadata",
      "roles": [
        "metadata"
      ]
    }
  },
  "bbox": [
    15.4195661658674,
    64.5110175916047,
    22.3139220984052,
    66.998962373709
  ],
  "stac_extensions": [],
  "collection": "sentinel_1_tiles_at_fmi",
  "gsd": 20.0,
  "proj:epsg": "EPSG:3067",
  "proj:transform": [
    20.0,
    0.0,
    -9686.881215289817,
    0.0,
    -20.0,
    7440383.341297286,
    0.0,
    0.0,
    1.0
  ]
}