{
  "type": "Feature",
  "stac_version": "1.0.0",
  "id": "Sentinel-1_VV_ja_VH_osakuvat_2019-06-08_152426",
  "properties": {
    "datetime": null,
    "start_datetime": "2019-06-08T15:24:26Z",
    "end_datetime": "2019-06-08T15:24:54Z",
    "orbit": "ASCENDING"
  },
  "geometry": {
    "type": "Polygon",
    "coordinates": [
      [
        [
          30.144573,
          61.498689
        ],
        [
          35.464926,
          61.270777
        ],
        [
          36.118242,
          63.484212
        ],
        [
          30.390711,
          63.734691
        ],
        [
          30.144573,
          61.498689
        ]
      ]
    ]
  },
  "links": [
    {
      "rel": "license",
      "href": "https://sentinels.copernicus.eu/documents/247904/690755/Sentinel_Data_Legal_Notice",
      "title": "License"
    },
    {
      "rel": "root",
      "href": "../../catalog.json",
      "type": "application/json"
    },
    {
      "rel": "collection",
      "href": "../collection.json",
      "type": "application/json",
      "title": "Sentinel-1 backscatter tiles: VV and VH polarisation."
    },
    {
      "rel": "parent",
      "href": "../collection.json",
      "type": "application/json",
      "title": "Sentinel-1 backscatter tiles: VV and VH polarisation."
    }
  ],
  "assets": {
    "vv": {
      "href": "https://pta.data.lit.fmi.fi/sen1/s1_grd_vv_prep/S1_processed_20190608_152426_152454_027590_031D11_VV.tif",
      "type": "image/tiff; application=geotiff; profile=cloud-optimized",
      "title": "vv",
      "roles": [
        "data"
      ]
    },
    "vh": {
      "href": "https://pta.data.lit.fmi.fi/sen1/s1_grd_vh_prep/S1_processed_20190608_152426_152454_027590_031D11_VH.tif",
      "type": "image/tiff; application=geotiff; profile=cloud-optimized",
      "title": "vh",
      "roles": [
        "data"
      ]
    },
    "metadata": {
      "href": "https://pta.data.lit.fmi.fi/sen1/s1_grd_meta_prep/S1_processed_20190608_152426_152454_027590_031D11.dim",
      "title": "metadata",
      "roles": [
        "metadata"
      ]
    }
  },
  "bbox": [
    30.14457346676,
    61.2707770023472,
    36.1182417450658,
    63.7346909058368
  ],
  "stac_extensions": [],
  "collection": "sentinel_1_tiles_at_fmi",
  "gsd": 20.0,
  "proj:epsg": "EPSG:3067",
  "proj:transform": [
    20.0,
    0.0,
    667358.2883375345,
    0.0,
    -20.0,
    7071893.16944733,
    0.0,
    0.0,
    1.0
  ]
}