{
  "type": "Feature",
  "stac_version": "1.0.0",
  "id": "Sentinel-1_VV_ja_VH_osakuvat_2020-04-01_042247",
  "properties": {
    "datetime": null,
    "start_datetime": "2020-04-01T04:22:47Z",
    "end_datetime": "2020-04-01T04:23:12Z",
    "orbit": "DESCENDING"
  },
  "geometry": {
    "type": "Polygon",
    "coordinates": [
      [
        [
          30.410038,
          69.212835
        ],
        [
          37.661119,
          68.91351
        ],
        [
          38.849091,
          71.087698
        ],
        [
          30.799429,
          71.42508
        ],
        [
          30.410038,
          69.212835
        ]
      ]
    ]
  },
  "links": [
    {
      "rel": "license",
      "href": "https://sentinels.copernicus.eu/documents/247904/690755/Sentinel_Data_Legal_Notice",
      "title": "License"
    },
    {
      "rel": "root",
      "href": "../../catalog.json",
      "type": "application/json"
    },
    {
      "rel": "collection",
      "href": "../collection.json",
      "type": "application/json",
      "title": "Sentinel-1 backscatter tiles: VV and VH polarisation."
    },
    {
      "rel": "parent",
      "href": "../collection.json",
      "type": "application/json",
      "title": "Sentinel-1 backscatter tiles: VV and VH polarisation."
    }
  ],
  "assets": {
    "vv": {
      "href": "https://pta.data.lit.fmi.fi/sen1/s1_grd_vv_prep/S1_processed_20200401_042247_042312_031929_03AFB9_VV.tif",
      "type": "image/tiff; application=geotiff; profile=cloud-optimized",
      "title": "vv",
      "roles": [
        "data"
      ]
    },
    "vh": {
      "href": "https://pta.data.lit.fmi.fi/sen1/s1_grd_vh_prep/S1_processed_20200401_042247_042312_031929_03AFB9_VH.tif",
      "type": "image/tiff; application=geotiff; profile=cloud-optimized",
      "title": "vh",
      "roles": [
        "data"
      ]
    },
    "metadata": {
      "href": "https://pta.data.lit.fmi.fi/sen1/s1_grd_meta_prep/S1_processed_20200401_042247_042312_031929_03AFB9.dim",
      "title": "metadata",
      "roles": [
        "metadata"
      ]
    }
  },
  "bbox": [
    30.4100378607719,
    68.913510343138,
    38.8490913324945,
    71.425079653227
  ],
  "stac_extensions": [],
  "collection": "sentinel_1_tiles_at_fmi",
  "gsd": 20.0,
  "proj:epsg": "EPSG:3067",
  "proj:transform": [
    20.0,
    0.0,
    635002.5859046074,
    0.0,
    -20.0,
    7929051.771719876,
    0.0,
    0.0,
    1.0
  ]
}