{
  "type": "Feature",
  "stac_version": "1.0.0",
  "id": "Sentinel-1_VV_ja_VH_osakuvat_2020-03-14_162936",
  "properties": {
    "datetime": null,
    "start_datetime": "2020-03-14T16:29:36Z",
    "end_datetime": "2020-03-14T16:30:01Z",
    "orbit": "ASCENDING"
  },
  "geometry": {
    "type": "Polygon",
    "coordinates": [
      [
        [
          15.205522,
          58.514537
        ],
        [
          20.33539,
          58.885495
        ],
        [
          19.872467,
          61.09947
        ],
        [
          14.403625,
          60.694477
        ],
        [
          15.205522,
          58.514537
        ]
      ]
    ]
  },
  "links": [
    {
      "rel": "root",
      "href": "../../catalog.json",
      "type": "application/json"
    },
    {
      "rel": "collection",
      "href": "../collection.json",
      "type": "application/json",
      "title": "Sentinel-1 backscatter tiles: VV and VH polarisation."
    },
    {
      "rel": "parent",
      "href": "../collection.json",
      "type": "application/json",
      "title": "Sentinel-1 backscatter tiles: VV and VH polarisation."
    }
  ],
  "assets": {
    "vv": {
      "href": "https://pta.data.lit.fmi.fi/sen1/s1_grd_vv_prep/S1_processed_20200314_162936_163001_031674_03A6CA_VV.tif",
      "type": "image/tiff; application=geotiff; profile=cloud-optimized",
      "title": "vv",
      "roles": [
        "data"
      ]
    },
    "vh": {
      "href": "https://pta.data.lit.fmi.fi/sen1/s1_grd_vh_prep/S1_processed_20200314_162936_163001_031674_03A6CA_VH.tif",
      "type": "image/tiff; application=geotiff; profile=cloud-optimized",
      "title": "vh",
      "roles": [
        "data"
      ]
    },
    "metadata": {
      "href": "https://pta.data.lit.fmi.fi/sen1/s1_grd_meta_prep/S1_processed_20200314_162936_163001_031674_03A6CA.dim",
      "title": "metadata",
      "roles": [
        "metadata"
      ]
    }
  },
  "bbox": [
    14.4036249220779,
    58.5145370726063,
    20.3353901238818,
    61.0994700392658
  ],
  "stac_extensions": [],
  "collection": "sentinel_1_tiles_at_fmi",
  "gsd": 20.0,
  "proj:epsg": "EPSG:3067",
  "proj:transform": [
    20.0,
    0.0,
    -184902.93510178418,
    0.0,
    -20.0,
    6794803.624674874,
    0.0,
    0.0,
    1.0
  ]
}