{
  "type": "Feature",
  "stac_version": "1.0.0",
  "id": "Sentinel-1_VV_ja_VH_osakuvat_2023-04-20_155817",
  "properties": {
    "datetime": null,
    "start_datetime": "2023-04-20T15:58:17Z",
    "end_datetime": "2023-04-20T15:58:42Z",
    "orbit": "ASCENDING"
  },
  "geometry": {
    "type": "Polygon",
    "coordinates": [
      [
        [
          21.083885,
          63.389708
        ],
        [
          26.620615,
          63.511712
        ],
        [
          26.591565,
          65.527625
        ],
        [
          20.634455,
          65.394152
        ],
        [
          21.083885,
          63.389708
        ]
      ]
    ]
  },
  "links": [
    {
      "rel": "root",
      "href": "../../catalog.json",
      "type": "application/json"
    },
    {
      "rel": "collection",
      "href": "../collection.json",
      "type": "application/json",
      "title": "Sentinel-1 backscatter tiles: VV and VH polarisation (FMI Tuulihaukka)"
    },
    {
      "rel": "parent",
      "href": "../collection.json",
      "type": "application/json",
      "title": "Sentinel-1 backscatter tiles: VV and VH polarisation (FMI Tuulihaukka)"
    }
  ],
  "assets": {
    "vv": {
      "href": "https://pta.data.lit.fmi.fi/sen1/s1_grd_vv_prep/S1_processed_20230420_155817_155842_048182_05CB03_VV.tif",
      "type": "image/tiff; application=geotiff; profile=cloud-optimized",
      "title": "vv",
      "roles": [
        "data"
      ]
    },
    "vh": {
      "href": "https://pta.data.lit.fmi.fi/sen1/s1_grd_vh_prep/S1_processed_20230420_155817_155842_048182_05CB03_VH.tif",
      "type": "image/tiff; application=geotiff; profile=cloud-optimized",
      "title": "vh",
      "roles": [
        "data"
      ]
    },
    "metadata": {
      "href": "https://pta.data.lit.fmi.fi/sen1/s1_grd_meta_prep/S1_processed_20230420_155817_155842_048182_05CB03.dim",
      "title": "metadata",
      "roles": [
        "metadata"
      ]
    }
  },
  "bbox": [
    20.6344550964887,
    63.3897083888674,
    26.6206148438467,
    65.5276250044062
  ],
  "stac_extensions": [],
  "collection": "sentinel_1_tiles_at_fmi",
  "gsd": 10.0,
  "proj:epsg": 3067,
  "proj:transform": [
    10.0,
    0.0,
    204650.39760837692,
    0.0,
    -10.0,
    7267320.6706521595,
    0.0,
    0.0,
    1.0
  ]
}