{
  "type": "Feature",
  "stac_version": "1.0.0",
  "id": "Sentinel-1_VV_ja_VH_osakuvat_2021-10-24_050313",
  "properties": {
    "datetime": null,
    "start_datetime": "2021-10-24T05:03:13Z",
    "end_datetime": "2021-10-24T05:04:33Z",
    "orbit": "DESCENDING"
  },
  "geometry": {
    "type": "Polygon",
    "coordinates": [
      [
        [
          19.336063,
          66.721769
        ],
        [
          28.537641,
          66.900566
        ],
        [
          28.963357,
          72.108177
        ],
        [
          17.249163,
          71.872775
        ],
        [
          19.336063,
          66.721769
        ]
      ]
    ]
  },
  "links": [
    {
      "rel": "root",
      "href": "../../catalog.json",
      "type": "application/json"
    },
    {
      "rel": "collection",
      "href": "../collection.json",
      "type": "application/json",
      "title": "Sentinel-1 backscatter tiles: VV and VH polarisation."
    },
    {
      "rel": "parent",
      "href": "../collection.json",
      "type": "application/json",
      "title": "Sentinel-1 backscatter tiles: VV and VH polarisation."
    }
  ],
  "assets": {
    "vv": {
      "href": "https://pta.data.lit.fmi.fi/sen1/s1_grd_vv_prep/S1_processed_20211024_050313_050433_029273_037E47_VV.tif",
      "type": "image/tiff; application=geotiff; profile=cloud-optimized",
      "title": "vv",
      "roles": [
        "data"
      ]
    },
    "vh": {
      "href": "https://pta.data.lit.fmi.fi/sen1/s1_grd_vh_prep/S1_processed_20211024_050313_050433_029273_037E47_VH.tif",
      "type": "image/tiff; application=geotiff; profile=cloud-optimized",
      "title": "vh",
      "roles": [
        "data"
      ]
    },
    "metadata": {
      "href": "https://pta.data.lit.fmi.fi/sen1/s1_grd_meta_prep/S1_processed_20211024_050313_050433_029273_037E47.dim",
      "title": "metadata",
      "roles": [
        "metadata"
      ]
    }
  },
  "bbox": [
    17.2491634020303,
    66.7217687851102,
    28.9633574559683,
    72.1081771680626
  ],
  "stac_extensions": [],
  "collection": "sentinel_1_tiles_at_fmi",
  "gsd": 10.0,
  "proj:epsg": "EPSG:3067",
  "proj:transform": [
    10.0,
    0.0,
    162713.0040389048,
    0.0,
    -10.0,
    8002096.486670226,
    0.0,
    0.0,
    1.0
  ]
}