{
  "type": "Feature",
  "stac_version": "1.0.0",
  "id": "Sentinel-1_VV_ja_VH_osakuvat_2019-10-03_052123",
  "properties": {
    "datetime": null,
    "start_datetime": "2019-10-03T05:21:23Z",
    "end_datetime": "2019-10-03T05:21:48Z",
    "orbit": "DESCENDING"
  },
  "geometry": {
    "type": "Polygon",
    "coordinates": [
      [
        [
          14.870971,
          65.457323
        ],
        [
          21.412119,
          65.841133
        ],
        [
          20.865447,
          68.106502
        ],
        [
          13.716231,
          67.679032
        ],
        [
          14.870971,
          65.457323
        ]
      ]
    ]
  },
  "links": [
    {
      "rel": "root",
      "href": "../../catalog.json",
      "type": "application/json"
    },
    {
      "rel": "collection",
      "href": "../collection.json",
      "type": "application/json",
      "title": "Sentinel-1 backscatter tiles: VV and VH polarisation."
    },
    {
      "rel": "parent",
      "href": "../collection.json",
      "type": "application/json",
      "title": "Sentinel-1 backscatter tiles: VV and VH polarisation."
    }
  ],
  "assets": {
    "vv": {
      "href": "https://pta.data.lit.fmi.fi/sen1/s1_grd_vv_prep/S1_processed_20191003_052123_052148_029290_03540E_VV.tif",
      "type": "image/tiff; application=geotiff; profile=cloud-optimized",
      "title": "vv",
      "roles": [
        "data"
      ]
    },
    "vh": {
      "href": "https://pta.data.lit.fmi.fi/sen1/s1_grd_vh_prep/S1_processed_20191003_052123_052148_029290_03540E_VH.tif",
      "type": "image/tiff; application=geotiff; profile=cloud-optimized",
      "title": "vh",
      "roles": [
        "data"
      ]
    },
    "metadata": {
      "href": "https://pta.data.lit.fmi.fi/sen1/s1_grd_meta_prep/S1_processed_20191003_052123_052148_029290_03540E.dim",
      "title": "metadata",
      "roles": [
        "metadata"
      ]
    }
  },
  "bbox": [
    13.7162309247298,
    65.4573227135949,
    21.4121189284702,
    68.1065018071235
  ],
  "stac_extensions": [],
  "collection": "sentinel_1_tiles_at_fmi",
  "gsd": 20.0,
  "proj:epsg": "EPSG:3067",
  "proj:transform": [
    20.0,
    0.0,
    -59402.15645711799,
    0.0,
    -20.0,
    7567416.644879306,
    0.0,
    0.0,
    1.0
  ]
}